[{"name":"render_template.action_view","payload":{"identifier":"/Users/hexaballs/Desktop/Gene Lim/Readable_App/app/views/welcome/index.html.erb","layout":"layouts/application"},"time":"2014-11-18T17:02:01.776+08:00","transaction_id":"12b464a7f499cbeb5ec5","end":"2014-11-18T17:02:01.777+08:00","children":[],"duration":1.343},{"name":"process_action.action_controller","payload":{"controller":"WelcomeController","action":"index","params":{"controller":"welcome","action":"index"},"format":"html","method":"GET","path":"/","status":200,"view_runtime":116.411,"db_runtime":0},"time":"2014-11-18T17:02:01.761+08:00","transaction_id":"12b464a7f499cbeb5ec5","end":"2014-11-18T17:02:01.886+08:00","children":[],"duration":124.931}]